pyreda/SimpleGA.py
pyreda/__init__.py
pyreda-0.1.5.dist-info/LICENSE
pyreda-0.1.5.dist-info/METADATA
pyreda-0.1.5.dist-info/WHEEL
pyreda-0.1.5.dist-info/top_level.txt
pyreda-0.1.5.dist-info/RECORD
