Metadata-Version: 2.1
Name: pyreda
Version: 0.1.5
Summary: A Python Library for Building the Genetic Algorithm.
Author: Reda Ghanem
Author-email: reda.ghanem66@gmail.com
Classifier: Programming Language :: Python :: 3
Classifier: License :: OSI Approved :: MIT License
Classifier: Operating System :: OS Independent
Requires-Python: >=3.6
License-File: LICENSE
Requires-Dist: numpy
Requires-Dist: pickle-mixin
Requires-Dist: joblib
Requires-Dist: pandas
Requires-Dist: matplotlib
